hopfield_model/__init__.py
hopfield_model/hopfield_model.py
HopfieldModel-1.0.1.dist-info/LICENSE
HopfieldModel-1.0.1.dist-info/METADATA
HopfieldModel-1.0.1.dist-info/WHEEL
HopfieldModel-1.0.1.dist-info/entry_points.txt
HopfieldModel-1.0.1.dist-info/top_level.txt
HopfieldModel-1.0.1.dist-info/RECORD
