Metadata-Version: 2.1
Name: HopfieldModel
Version: 1.0.1
Summary: A Python package to model single-cell data using Hopfield networks
Author-email: Ashish Phal <aphal@uw.edu>
License: MIT
Project-URL: homepage, https://github.com/ashx56/scHopfield
Keywords: hopfield,network,single-cell,bioinformatics
Classifier: Intended Audience :: Science/Research
Classifier: License :: OSI Approved :: MIT License
Classifier: Programming Language :: Python :: 3
Classifier: Topic :: Scientific/Engineering :: Bio-Informatics
Requires-Python: >=3.7
License-File: LICENSE
Requires-Dist: numpy
Requires-Dist: matplotlib
Requires-Dist: scikit-learn
Requires-Dist: scanpy
Requires-Dist: seaborn
Requires-Dist: scipy
Provides-Extra: dev
Requires-Dist: pytest; extra == "dev"
Requires-Dist: black; extra == "dev"
Requires-Dist: flake8; extra == "dev"
